sentinel_mock_plan/__init__.py
sentinel_mock_plan/__main__.py
sentinel_mock_plan-0.3.0.dist-info/LICENSE
sentinel_mock_plan-0.3.0.dist-info/WHEEL
sentinel_mock_plan-0.3.0.dist-info/METADATA
sentinel_mock_plan-0.3.0.dist-info/RECORD
