Metadata-Version: 2.1
Name: sentinel-mock-plan
Version: 0.3.0
Summary: Create a mock plan for Hashicorp Sentinel 0.26.2
Author: Amine Laabi
Author-email: amine.laabi@outlook.fr
Requires-Python: >=3.12,<4.0
Classifier: Programming Language :: Python :: 3
